<?xml version="1.0" encoding="UTF-8" ?>
<runHistory script="OpenEMR_Launch">
 <run>
  <RunDate>2024-03-26 15:48:45.727 -0400</RunDate>
  <Status>Success</Status>
  <Duration>17.001000</Duration>
  <Errors>0</Errors>
  <Warnings>0</Warnings>
  <Exceptions>0</Exceptions>
  <Successes>1</Successes>
  <LogFile>20240326_154845.727/LogFile.txt</LogFile>
  <ReturnValue></ReturnValue>
  <ErrorMessage></ErrorMessage>
 </run>
 <run>
  <RunDate>2024-07-11 13:17:48.027 -0400</RunDate>
  <Status>Success</Status>
  <Duration>70.732000</Duration>
  <Errors>0</Errors>
  <Warnings>0</Warnings>
  <Exceptions>0</Exceptions>
  <Successes>1</Successes>
  <LogFile>20240711_131748.027/LogFile.txt</LogFile>
  <ReturnValue></ReturnValue>
  <ErrorMessage></ErrorMessage>
 </run>
 <run>
  <RunDate>2024-07-17 22:24:49.615 -0400</RunDate>
  <Status>Success</Status>
  <Duration>233.488000</Duration>
  <Errors>0</Errors>
  <Warnings>0</Warnings>
  <Exceptions>0</Exceptions>
  <Successes>1</Successes>
  <LogFile>20240717_222449.615/LogFile.txt</LogFile>
  <ReturnValue></ReturnValue>
  <ErrorMessage></ErrorMessage>
 </run>
 <run>
  <RunDate>2024-07-17 22:37:58.852 -0400</RunDate>
  <Status>Success</Status>
  <Duration>2.113000</Duration>
  <Errors>0</Errors>
  <Warnings>0</Warnings>
  <Exceptions>0</Exceptions>
  <Successes>1</Successes>
  <LogFile>20240717_223758.852/LogFile.txt</LogFile>
  <ReturnValue></ReturnValue>
  <ErrorMessage></ErrorMessage>
 </run>
 <run>
  <RunDate>2025-02-26 09:12:36.564 -0500</RunDate>
  <Status>Aborted</Status>
  <Duration>99.620000</Duration>
  <Errors>1</Errors>
  <Warnings>0</Warnings>
  <Exceptions>2</Exceptions>
  <Successes>0</Successes>
  <LogFile>20250226_091236.564/LogFile.txt</LogFile>
  <ReturnValue></ReturnValue>
  <ErrorMessage></ErrorMessage>
 </run>
 <run>
  <RunDate>2025-02-26 09:14:18.594 -0500</RunDate>
  <Status>Aborted</Status>
  <Duration>55.400000</Duration>
  <Errors>1</Errors>
  <Warnings>0</Warnings>
  <Exceptions>2</Exceptions>
  <Successes>0</Successes>
  <LogFile>20250226_091418.594/LogFile.txt</LogFile>
  <ReturnValue></ReturnValue>
  <ErrorMessage></ErrorMessage>
 </run>
 <run>
  <RunDate>2025-02-26 09:15:35.400 -0500</RunDate>
  <Status>Aborted</Status>
  <Duration>73.740000</Duration>
  <Errors>1</Errors>
  <Warnings>0</Warnings>
  <Exceptions>1</Exceptions>
  <Successes>0</Successes>
  <LogFile>20250226_091535.400/LogFile.txt</LogFile>
  <ReturnValue></ReturnValue>
  <ErrorMessage></ErrorMessage>
 </run>
 <run>
  <RunDate>2025-02-26 09:17:24.784 -0500</RunDate>
  <Status>Success</Status>
  <Duration>8.629000</Duration>
  <Errors>0</Errors>
  <Warnings>0</Warnings>
  <Exceptions>0</Exceptions>
  <Successes>1</Successes>
  <LogFile>20250226_091724.784/LogFile.txt</LogFile>
  <ReturnValue></ReturnValue>
  <ErrorMessage></ErrorMessage>
 </run>
 <run>
  <RunDate>2025-02-26 15:51:07.749 -0500</RunDate>
  <Status>Failure</Status>
  <Duration>0.111000</Duration>
  <Errors>1</Errors>
  <Warnings>0</Warnings>
  <Exceptions>0</Exceptions>
  <Successes>0</Successes>
  <LogFile>20250226_155107.749/LogFile.txt</LogFile>
  <ReturnValue></ReturnValue>
  <ErrorMessage>STUnknownMessage -- ERROR: No Such Function: &#x27;screenpart&#x27;</ErrorMessage>
 </run>
 <run>
  <RunDate>2025-02-26 15:59:43.731 -0500</RunDate>
  <Status>Aborted</Status>
  <Duration>153.559000</Duration>
  <Errors>1</Errors>
  <Warnings>0</Warnings>
  <Exceptions>0</Exceptions>
  <Successes>0</Successes>
  <LogFile>20250226_155943.731/LogFile.txt</LogFile>
  <ReturnValue></ReturnValue>
  <ErrorMessage></ErrorMessage>
 </run>
 <run>
  <RunDate>2025-02-26 16:04:27.778 -0500</RunDate>
  <Status>Aborted</Status>
  <Duration>515.340000</Duration>
  <Errors>1</Errors>
  <Warnings>0</Warnings>
  <Exceptions>1</Exceptions>
  <Successes>0</Successes>
  <LogFile>20250226_160427.778/LogFile.txt</LogFile>
  <ReturnValue></ReturnValue>
  <ErrorMessage></ErrorMessage>
 </run>
 <run>
  <RunDate>2025-02-26 16:14:21.434 -0500</RunDate>
  <Status>Aborted</Status>
  <Duration>619.090000</Duration>
  <Errors>1</Errors>
  <Warnings>0</Warnings>
  <Exceptions>1</Exceptions>
  <Successes>0</Successes>
  <LogFile>20250226_161421.434/LogFile.txt</LogFile>
  <ReturnValue></ReturnValue>
  <ErrorMessage></ErrorMessage>
 </run>
 <run>
  <RunDate>2025-02-26 16:28:04.118 -0500</RunDate>
  <Status>Success</Status>
  <Duration>25.690000</Duration>
  <Errors>0</Errors>
  <Warnings>0</Warnings>
  <Exceptions>0</Exceptions>
  <Successes>1</Successes>
  <LogFile>20250226_162804.118/LogFile.txt</LogFile>
  <ReturnValue></ReturnValue>
  <ErrorMessage></ErrorMessage>
 </run>
</runHistory>
